[
  {
    "author": "Eric33164",
    "link_thumb": "https://live.staticflickr.com/65535/51669626521_3009540fcf_o.gif",
    "link_bin": "https://github.com/lmbstudiocontact/mb6_1/raw/main/2234.bin",
    "id_bin": "2234",
    "list_language": [],
    "array_tags": [
      "digital",
      "date",
      "seconds",
      "heartrate",
      "weather",
      "battery"
    ],
    "list_album": [
      {
        "id_album": "2433880",
        "link_thumb": "https://live.staticflickr.com/65535/51669626521_3009540fcf_o.gif",
        "title": "None"
      }
    ]
  },
  {
    "author": "CTEPE0",
    "link_thumb": "https://live.staticflickr.com/65535/51670425554_41b2766e53_o.gif",
    "link_bin": "https://github.com/lmbstudiocontact/mb6_0/raw/main/581.bin",
    "id_bin": "581",
    "list_language": [],
    "array_tags": [
      "minecraft",
      "animation"
    ],
    "list_album": [
      {
        "id_album": "-2075887794",
        "link_thumb": "https://live.staticflickr.com/65535/51670425554_41b2766e53_o.gif",
        "title": "Cartoon"
      }
    ]
  },
  {
    "author": "zekixfly",
    "link_thumb": "https://live.staticflickr.com/65535/51670349290_8e45c8ebaf_o.gif",
    "link_bin": "https://github.com/lmbstudiocontact/mb6_0/raw/main/1083.bin",
    "id_bin": "1083",
    "list_language": [],
    "array_tags": [
      "date",
      "analog",
      "heartrate",
      "time",
      "steps"
    ],
    "list_album": [
      {
        "id_album": "2433880",
        "link_thumb": "https://live.staticflickr.com/65535/51670349290_8e45c8ebaf_o.gif",
        "title": "None"
      }
    ]
  },
  {
    "author": "mpsspencer",
    "link_thumb": "https://live.staticflickr.com/65535/51670681760_61712085b8_o.gif",
    "link_bin": "https://github.com/lmbstudiocontact/mb6_0/raw/main/893.bin",
    "id_bin": "893",
    "list_language": [],
    "array_tags": [
      "date",
      "digital",
      "distance",
      "notdisturb",
      "heartrate",
      "stars",
      "calories",
      "kcal",
      "bluetooth",
      "alarm",
      "weather",
      "pai",
      "lock",
      "day"
    ],
    "list_album": [
      {
        "id_album": "2433880",
        "link_thumb": "https://live.staticflickr.com/65535/51670681760_61712085b8_o.gif",
        "title": "None"
      }
    ]
  },
  {
    "author": "KA1OTE",
    "link_thumb": "https://live.staticflickr.com/65535/51669626661_6c907e0008_o.gif",
    "link_bin": "https://github.com/lmbstudiocontact/mb6_1/raw/main/2235.bin",
    "id_bin": "2235",
    "list_language": [],
    "array_tags": [
      "digital",
      "date",
      "month",
      "heartrate",
      "pulse",
      "time",
      "battery",
      "day",
      "steps"
    ],
    "list_album": [
      {
        "id_album": "2433880",
        "link_thumb": "https://live.staticflickr.com/65535/51669626661_6c907e0008_o.gif",
        "title": "None"
      }
    ]
  },
  {
    "author": "gfzt",
    "link_thumb": "https://live.staticflickr.com/65535/51670579900_1132fa0e3b_o.gif",
    "link_bin": "https://github.com/lmbstudiocontact/mb6_0/raw/main/4.bin",
    "id_bin": "4",
    "list_language": [],
    "array_tags": [
      "date",
      "heartrate",
      "steps"
    ],
    "list_album": [
      {
        "id_album": "-2075887794",
        "link_thumb": "https://live.staticflickr.com/65535/51670579900_1132fa0e3b_o.gif",
        "title": "Cartoon"
      }
    ]
  },
  {
    "author": "sebastianvila",
    "link_thumb": "https://live.staticflickr.com/65535/51670403129_eb63208916_o.gif",
    "link_bin": "https://github.com/lmbstudiocontact/mb6_0/raw/main/474.bin",
    "id_bin": "474",
    "list_language": [],
    "array_tags": [
      "boca",
      "simple"
    ],
    "list_album": [
      {
        "id_album": "2433880",
        "link_thumb": "https://live.staticflickr.com/65535/51670403129_eb63208916_o.gif",
        "title": "None"
      }
    ]
  },
  {
    "author": "perseusbc",
    "link_thumb": "https://live.staticflickr.com/65535/51670614535_b8aedfb317_o.gif",
    "link_bin": "https://github.com/lmbstudiocontact/mb6_0/raw/main/568.bin",
    "id_bin": "568",
    "list_language": [],
    "array_tags": [
      "digital",
      "date",
      "analog",
      "distance",
      "heartrate",
      "weather",
      "calories",
      "battery",
      "steps"
    ],
    "list_album": [
      {
        "id_album": "2433880",
        "link_thumb": "https://live.staticflickr.com/65535/51670614535_b8aedfb317_o.gif",
        "title": "None"
      }
    ]
  },
  {
    "author": "Phobos666",
    "link_thumb": "https://live.staticflickr.com/65535/51669711496_bf047067f9_o.gif",
    "link_bin": "https://github.com/lmbstudiocontact/mb6_0/raw/main/453.bin",
    "id_bin": "453",
    "list_language": [],
    "array_tags": [
      "pai"
    ],
    "list_album": [
      {
        "id_album": "2433880",
        "link_thumb": "https://live.staticflickr.com/65535/51669711496_bf047067f9_o.gif",
        "title": "None"
      }
    ]
  },
  {
    "author": "magnim",
    "link_thumb": "https://live.staticflickr.com/65535/51668948567_f0a37030e6_o.gif",
    "link_bin": "https://github.com/lmbstudiocontact/mb6_0/raw/main/618.bin",
    "id_bin": "618",
    "list_language": [],
    "array_tags": [
      "digital",
      "amoled",
      "weather",
      "pulse",
      "calories",
      "steps",
      "colors"
    ],
    "list_album": [
      {
        "id_album": "2433880",
        "link_thumb": "https://live.staticflickr.com/65535/51668948567_f0a37030e6_o.gif",
        "title": "None"
      }
    ]
  },
  {
    "author": "KrakeCZ",
    "link_thumb": "https://live.staticflickr.com/65535/51670151804_91d31e90db_o.gif",
    "link_bin": "https://github.com/lmbstudiocontact/mb6_0/raw/main/1041.bin",
    "id_bin": "1041",
    "list_language": [],
    "array_tags": [
      "digital",
      "date",
      "distance",
      "heartrate",
      "weather",
      "calories",
      "battery",
      "steps"
    ],
    "list_album": [
      {
        "id_album": "2433880",
        "link_thumb": "https://live.staticflickr.com/65535/51670151804_91d31e90db_o.gif",
        "title": "None"
      }
    ]
  },
  {
    "author": "TsReal30",
    "link_thumb": "https://live.staticflickr.com/65535/51669758958_e678bd3c66_o.gif",
    "link_bin": "https://github.com/lmbstudiocontact/mb6_0/raw/main/149.bin",
    "id_bin": "149",
    "list_language": [],
    "array_tags": [
      "digital",
      "ultrainstint",
      "goku",
      "retro"
    ],
    "list_album": [
      {
        "id_album": "63410260",
        "link_thumb": "https://live.staticflickr.com/65535/51669758958_e678bd3c66_o.gif",
        "title": "Anime"
      }
    ]
  }
]